novel_downloader/__init__.py
novel_downloader/__main__.py
novel_downloader/apps/__init__.py
novel_downloader/apps/constants.py
novel_downloader/apps/utils.py
novel_downloader/apps/cli/__init__.py
novel_downloader/apps/cli/interactive.py
novel_downloader/apps/cli/main.py
novel_downloader/apps/cli/prompts.py
novel_downloader/apps/cli/ui.py
novel_downloader/apps/cli/ui_adapters.py
novel_downloader/apps/cli/commands/__init__.py
novel_downloader/apps/cli/commands/base.py
novel_downloader/apps/cli/commands/clean.py
novel_downloader/apps/cli/commands/config.py
novel_downloader/apps/cli/commands/download.py
novel_downloader/apps/cli/commands/export.py
novel_downloader/apps/cli/commands/search.py
novel_downloader/apps/web/__init__.py
novel_downloader/apps/web/main.py
novel_downloader/apps/web/models.py
novel_downloader/apps/web/ui_adapters.py
novel_downloader/apps/web/components/__init__.py
novel_downloader/apps/web/components/navigation.py
novel_downloader/apps/web/pages/__init__.py
novel_downloader/apps/web/pages/download.py
novel_downloader/apps/web/pages/history.py
novel_downloader/apps/web/pages/progress.py
novel_downloader/apps/web/pages/search.py
novel_downloader/apps/web/services/__init__.py
novel_downloader/apps/web/services/client_dialog.py
novel_downloader/apps/web/services/cred_broker.py
novel_downloader/apps/web/services/task_manager.py
novel_downloader/infra/__init__.py
novel_downloader/infra/book_url_resolver.py
novel_downloader/infra/cookies.py
novel_downloader/infra/http_defaults.py
novel_downloader/infra/i18n.py
novel_downloader/infra/logger.py
novel_downloader/infra/network.py
novel_downloader/infra/paths.py
novel_downloader/infra/config/__init__.py
novel_downloader/infra/config/adapter.py
novel_downloader/infra/config/file_io.py
novel_downloader/infra/jsbridge/__init__.py
novel_downloader/infra/jsbridge/decryptor.py
novel_downloader/infra/jsbridge/decryptor_fetcher.py
novel_downloader/infra/persistence/__init__.py
novel_downloader-2.5.0.dist-info/licenses/LICENSE
novel_downloader-2.5.0.dist-info/METADATA
novel_downloader-2.5.0.dist-info/WHEEL
novel_downloader-2.5.0.dist-info/entry_points.txt
novel_downloader-2.5.0.dist-info/top_level.txt
novel_downloader-2.5.0.dist-info/RECORD
