Metadata-Version: 2.4
Name: novel-downloader
Version: 2.5.0
Summary: A command-line tool for downloading Chinese web novels from Qidian and similar platforms.
Author-email: Saudade Z <saudadez217@gmail.com>
License: MIT License
Project-URL: Homepage, https://github.com/saudadez21/novel-downloader
Project-URL: Source, https://github.com/saudadez21/novel-downloader
Keywords: novel,web novel,qidian,biquge,ebook
Classifier: Development Status :: 3 - Alpha
Classifier: Environment :: Console
Classifier: License :: OSI Approved :: MIT License
Classifier: Natural Language :: Chinese (Simplified)
Classifier: Topic :: Utilities
Classifier: Programming Language :: Python :: 3
Classifier: Programming Language :: Python :: 3.11
Classifier: Programming Language :: Python :: 3.12
Classifier: Programming Language :: Python :: 3.13
Requires-Python: >=3.11
License-File: LICENSE
Requires-Dist: rich
Requires-Dist: nicegui
Requires-Dist: requests
Requires-Dist: pycryptodome
Requires-Dist: aiohttp
Requires-Dist: lxml
Requires-Dist: platformdirs
Provides-Extra: font-recovery
Requires-Dist: brotli; extra == "font-recovery"
Requires-Dist: numpy; extra == "font-recovery"
Requires-Dist: fonttools; extra == "font-recovery"
Requires-Dist: pillow; extra == "font-recovery"
Provides-Extra: dev
Requires-Dist: black; extra == "dev"
Requires-Dist: mypy; extra == "dev"
Requires-Dist: ruff; extra == "dev"
Requires-Dist: pytest; extra == "dev"
Requires-Dist: pytest-asyncio; extra == "dev"
Requires-Dist: pytest-cov; extra == "dev"
Requires-Dist: pytest-mock; extra == "dev"
Requires-Dist: types-requests; extra == "dev"
Requires-Dist: types-lxml; extra == "dev"
Requires-Dist: types-PyYAML; extra == "dev"
Requires-Dist: pre-commit; extra == "dev"
Requires-Dist: commitizen; extra == "dev"
Requires-Dist: babel; extra == "dev"
Dynamic: license-file
